napari_dinosim/__init__.py
napari_dinosim/_widget.py
napari_dinosim/napari.yaml
napari_dinosim/_tests/__init__.py
napari_dinosim/_tests/test_pipeline.py
napari_dinosim/utils/__init__.py
napari_dinosim/utils/data_utils_biapy.py
napari_dinosim/utils/dinoSim_pipeline.py
napari_dinosim/utils/gui_utils.py
napari_dinosim/utils/sam2_utils.py
napari_dinosim/utils/utils.py
napari_dinosim-0.1.3.dist-info/licenses/LICENSE
napari_dinosim-0.1.3.dist-info/METADATA
napari_dinosim-0.1.3.dist-info/WHEEL
napari_dinosim-0.1.3.dist-info/entry_points.txt
napari_dinosim-0.1.3.dist-info/top_level.txt
napari_dinosim-0.1.3.dist-info/RECORD
