Metadata-Version: 2.4
Name: napari-dinosim
Version: 0.1.3
Summary: A simple plugin to use DINOSim in napari
Author: Aitor Gonzalez-Marfil
Author-email: aitorgacad@gmail.com
License: MIT License
Project-URL: Documentation, https://github.com/AAitorG/napari-DINOSim#readme
Project-URL: Repository, https://github.com/AAitorG/napari-DINOSim
Project-URL: Issues, https://github.com/AAitorG/napari-DINOSim/issues
Classifier: Development Status :: 3 - Alpha
Classifier: Framework :: napari
Classifier: Intended Audience :: Developers
Classifier: Intended Audience :: Science/Research
Classifier: License :: OSI Approved :: MIT License
Classifier: Operating System :: OS Independent
Classifier: Programming Language :: Python
Classifier: Programming Language :: Python :: 3
Classifier: Programming Language :: Python :: 3 :: Only
Classifier: Programming Language :: Python :: 3.9
Classifier: Programming Language :: Python :: 3.10
Classifier: Programming Language :: Python :: 3.11
Classifier: Programming Language :: Python :: 3.12
Classifier: Topic :: Scientific/Engineering :: Image Processing
Classifier: Topic :: Scientific/Engineering :: Artificial Intelligence
Requires-Python: <3.13,>=3.9
License-File: LICENSE
Requires-Dist: numpy
Requires-Dist: magicgui
Requires-Dist: qtpy
Requires-Dist: torch
Requires-Dist: torchvision
Requires-Dist: tqdm
Requires-Dist: pillow
Requires-Dist: matplotlib
Requires-Dist: opencv-python
Requires-Dist: tifffile
Requires-Dist: napari[all]
Provides-Extra: testing
Requires-Dist: tox; extra == "testing"
Requires-Dist: pytest>=8.3.5; extra == "testing"
Requires-Dist: pytest-qt>=4.4.0; extra == "testing"
Requires-Dist: pytest-xvfb>=3.0.0; extra == "testing"
Requires-Dist: pytest-cov>=6.0; extra == "testing"
Requires-Dist: pyqt5>=5.15.11; extra == "testing"
Requires-Dist: napari>=0.5.6; extra == "testing"
Requires-Dist: magicgui>=0.10.0; extra == "testing"
Dynamic: license-file
